open_responses_server/__init__.py
open_responses_server/api_controller.py
open_responses_server/chat_completions_service.py
open_responses_server/cli.py
open_responses_server/is_mcp_tool.py
open_responses_server/mcp-chatbot-client.py
open_responses_server/responses_service.py
open_responses_server/server.py
open_responses_server/server_entrypoint.py
open_responses_server/version.py
open_responses_server/common/__init__.py
open_responses_server/common/config.py
open_responses_server/common/llm_client.py
open_responses_server/common/mcp_manager.py
open_responses_server/models/__init__.py
open_responses_server/models/responses_models.py
open_responses_server-0.4.1.dist-info/licenses/LICENSE
open_responses_server-0.4.1.dist-info/METADATA
open_responses_server-0.4.1.dist-info/WHEEL
open_responses_server-0.4.1.dist-info/entry_points.txt
open_responses_server-0.4.1.dist-info/top_level.txt
open_responses_server-0.4.1.dist-info/RECORD
