Metadata-Version: 2.4
Name: open-responses-server
Version: 0.4.1
Summary: CLI to manage the OpenAI Responses Server that bridges chat completions to responses API calls
Home-page: https://github.com/teabranch/open-responses-server
Author: Ori Nachum
Author-email: Ori Nachum <ori.nachum@gmail.com>
License: MIT
Project-URL: Homepage, https://github.com/teabranch/open-responses-server
Project-URL: Documentation, https://github.com/teabranch/open-responses-server
Project-URL: Repository, https://github.com/teabranch/open-responses-server
Classifier: Programming Language :: Python :: 3
Classifier: License :: OSI Approved :: MIT License
Classifier: Operating System :: OS Independent
Classifier: Environment :: Web Environment
Requires-Python: >=3.7
License-File: LICENSE
Requires-Dist: mcp>=1.0.0
Requires-Dist: fastapi>=0.68.0
Requires-Dist: uvicorn>=0.15.0
Requires-Dist: httpx>=0.24.0
Requires-Dist: python-dotenv>=0.19.0
Requires-Dist: pydantic>=1.8.0
Requires-Dist: requests>=2.31.0
Provides-Extra: dev
Requires-Dist: pytest>=6.0; extra == "dev"
Requires-Dist: black>=21.0; extra == "dev"
Requires-Dist: flake8>=3.9; extra == "dev"
Requires-Dist: twine>=6.1.0; extra == "dev"
Requires-Dist: pylint>=2.17.0; extra == "dev"
Requires-Dist: bandit>=1.7.5; extra == "dev"
Requires-Dist: pre-commit>=3.3.0; extra == "dev"
Requires-Dist: coverage>=7.2.0; extra == "dev"
Requires-Dist: flake8-bandit>=4.1.1; extra == "dev"
Requires-Dist: flake8-bugbear>=23.7.10; extra == "dev"
Requires-Dist: uvicorn>=0.32.1; extra == "dev"
Dynamic: author
Dynamic: home-page
Dynamic: license-file
Dynamic: requires-python
